Metadata-Version: 1.0
Name: jhkim-probability
Version: 0.1
Summary: Gaussian and Binomial distributions
Home-page: UNKNOWN
Author: Ji-Hoon Kim
Author-email: genesis717.jhk@gmail.com
License: UNKNOWN
Platform: UNKNOWN
